ndarraybuffer/__init__.py
ndarraybuffer/array_buffer.py
ndarraybuffer/py.typed
ndarraybuffer-0.2.1.dist-info/METADATA
ndarraybuffer-0.2.1.dist-info/WHEEL
ndarraybuffer-0.2.1.dist-info/RECORD
