Metadata-Version: 2.1
Name: ndarraybuffer
Version: 0.2.1
Summary: NDArray with both-side insertion/deletion and size limit
License: MIT
Author: Zeyan Li 李则言
Author-email: lizeyan.42@bytedance.com
Requires-Python: >=3.10,<4.0
Classifier: License :: OSI Approved :: MIT License
Classifier: Programming Language :: Python :: 3
Classifier: Programming Language :: Python :: 3.10
Classifier: Programming Language :: Python :: 3.11
Classifier: Programming Language :: Python :: 3.12
Classifier: Programming Language :: Python :: 3.13
Requires-Dist: numpy (>=1.21)
